test.py
mflow/__init__.py
mflow/app.py
mflow/config.py
mflow/constants.py
mflow/exceptions.py
mflow/handler.py
mflow/link_info.py
mflow/utils.py
mflow-1.3.1.dist-info/licenses/LICENSE
mflow-1.3.1.dist-info/METADATA
mflow-1.3.1.dist-info/WHEEL
mflow-1.3.1.dist-info/entry_points.txt
mflow-1.3.1.dist-info/top_level.txt
mflow-1.3.1.dist-info/RECORD
