Metadata-Version: 2.4
Name: mflow
Version: 1.3.1
Summary: Multi Flow - Concurrent Streaming Proxy
Author-email: UkiyoDevs <ukiyodev@foxmail.com>
License: Apache-2.0
Requires-Python: >=3.9
License-File: LICENSE
Requires-Dist: aiohttp>=3.11.16
Requires-Dist: bytesparse>=1.0.1
Requires-Dist: colorama>=0.4.6
Dynamic: license-file
